cdk_s3_upload_presignedurl_api/__init__.py
cdk_s3_upload_presignedurl_api/py.typed
cdk_s3_upload_presignedurl_api/_jsii/__init__.py
cdk_s3_upload_presignedurl_api/_jsii/cdk-s3-upload-presignedurl-api@0.0.7.jsii.tgz
cdk_s3_upload_presignedurl_api-0.0.7.dist-info/LICENSE
cdk_s3_upload_presignedurl_api-0.0.7.dist-info/METADATA
cdk_s3_upload_presignedurl_api-0.0.7.dist-info/WHEEL
cdk_s3_upload_presignedurl_api-0.0.7.dist-info/top_level.txt
cdk_s3_upload_presignedurl_api-0.0.7.dist-info/RECORD
